LICENSE
dustpan/__init__.py
dustpan/__main__.py
dustpan/config.py
dustpan-0.3.3.dist-info/LICENSE
dustpan-0.3.3.dist-info/METADATA
dustpan-0.3.3.dist-info/WHEEL
dustpan-0.3.3.dist-info/entry_points.txt
dustpan-0.3.3.dist-info/RECORD
