Metadata-Version: 2.1
Name: dustpan
Version: 0.3.3
Summary: 
Home-page: https://github.com/dawsonbooth/dustpan
License: MIT
Author: Dawson Booth
Author-email: pypi@dawsonbooth.com
Requires-Python: >=3.8.1,<4.0.0
Classifier: Environment :: Console
Classifier: License :: OSI Approved :: MIT License
Classifier: Operating System :: OS Independent
Classifier: Programming Language :: Python :: 3
Classifier: Programming Language :: Python :: 3.9
Classifier: Programming Language :: Python :: 3.10
Classifier: Programming Language :: Python :: 3.11
Classifier: Programming Language :: Python :: 3
Requires-Dist: attrs (>=22.2.0,<23.0.0)
Requires-Dist: colorama (>=0.4.6,<0.5.0)
Requires-Dist: toml (>=0.10.2,<0.11.0)
Project-URL: Documentation, https://dawsonbooth.github.io/dustpan
Project-URL: Repository, https://github.com/dawsonbooth/dustpan
